galaxy_test/__init__.py
galaxy_test/py.typed
galaxy_test/api/__init__.py
galaxy_test/api/_framework.py
galaxy_test/api/conftest.py
galaxy_test/api/embed_test_1.gxwf.yml
galaxy_test/api/embed_test_1_tool.gxtool.yml
galaxy_test/api/sharable.py
galaxy_test/api/test_authenticate.py
galaxy_test/api/test_configuration.py
galaxy_test/api/test_container_resolution.py
galaxy_test/api/test_dataset_collections.py
galaxy_test/api/test_datasets.py
galaxy_test/api/test_datatypes.py
galaxy_test/api/test_display_applications.py
galaxy_test/api/test_drs.py
galaxy_test/api/test_folder_contents.py
galaxy_test/api/test_folders.py
galaxy_test/api/test_framework.py
galaxy_test/api/test_group_roles.py
galaxy_test/api/test_group_users.py
galaxy_test/api/test_groups.py
galaxy_test/api/test_histories.py
galaxy_test/api/test_history_contents.py
galaxy_test/api/test_history_contents_provenance.py
galaxy_test/api/test_item_tags.py
galaxy_test/api/test_jobs.py
galaxy_test/api/test_landing.py
galaxy_test/api/test_libraries.py
galaxy_test/api/test_library_contents.py
galaxy_test/api/test_licenses.py
galaxy_test/api/test_page_revisions.py
galaxy_test/api/test_pages.py
galaxy_test/api/test_proxy.py
galaxy_test/api/test_roles.py
galaxy_test/api/test_short_term_storage.py
galaxy_test/api/test_tags.py
galaxy_test/api/test_tool_data.py
galaxy_test/api/test_tool_execute.py
galaxy_test/api/test_tools.py
galaxy_test/api/test_tools_upload.py
galaxy_test/api/test_tours.py
galaxy_test/api/test_unprivileged_tools.py
galaxy_test/api/test_users.py
galaxy_test/api/test_visualizations.py
galaxy_test/api/test_webhooks.py
galaxy_test/api/test_workflow_build_module.py
galaxy_test/api/test_workflow_extraction.py
galaxy_test/api/test_workflows.py
galaxy_test/api/test_workflows_cwl.py
galaxy_test/api/test_workflows_from_yaml.py
galaxy_test/api/cwl/__init__.py
galaxy_test_api-25.0.3.dist-info/licenses/LICENSE
galaxy_test_api-25.0.3.dist-info/METADATA
galaxy_test_api-25.0.3.dist-info/WHEEL
galaxy_test_api-25.0.3.dist-info/top_level.txt
galaxy_test_api-25.0.3.dist-info/RECORD
